{
  "category": "style",
  "total_items": 50,
  "discovery_method": "Dynamic category discovery",
  "last_updated": "2025-09-07T15:54:00.590Z",
  "source": "FatSecret Platform API (OAuth 1.0)",
  "items": [
    {
      "food_id": "3058",
      "food_name": "Cream Style Salmon Soup",
      "food_url": "https://foods.fatsecret.com/calories-nutrition/generic/salmon-soup-cream-style",
      "brand_name": "",
      "food_type": "Generic"
    },
    {
      "food_id": "6518",
      "food_name": "Cream Style Yellow Corn",
      "food_url": "https://foods.fatsecret.com/calories-nutrition/generic/corn-yellow-cream-style",
      "brand_name": "",
      "food_type": "Generic"
    },
    {
      "food_id": "6889",
      "food_name": "Japanese Style Pickled Cabbage",
      "food_url": "https://foods.fatsecret.com/calories-nutrition/generic/cabbage-fresh-pickled-japanese-style",
      "brand_name": "",
      "food_type": "Generic"
    },
    {
      "food_id": "7418",
      "food_name": "Oriental Style Plum Sauce",
      "food_url": "https://foods.fatsecret.com/calories-nutrition/generic/plum-sauce-oriental-style",
      "brand_name": "",
      "food_type": "Generic"
    },
    {
      "food_id": "5813",
      "food_name": "German Style Potato Salad",
      "food_url": "https://foods.fatsecret.com/calories-nutrition/generic/potato-salad-german-style",
      "brand_name": "",
      "food_type": "Generic"
    },
    {
      "food_id": "6446",
      "food_name": "Cream Style White Corn",
      "food_url": "https://foods.fatsecret.com/calories-nutrition/generic/corn-white-cream-style",
      "brand_name": "",
      "food_type": "Generic"
    },
    {
      "food_id": "6542",
      "food_name": "Cream Style Corn",
      "food_url": "https://foods.fatsecret.com/calories-nutrition/generic/corn-ns-as-to-color-cream-style",
      "brand_name": "",
      "food_type": "Generic"
    },
    {
      "food_id": "6815",
      "food_name": "Hawaiian Style Pickled Vegetables",
      "food_url": "https://foods.fatsecret.com/calories-nutrition/generic/vegetables-pickled-hawaiian-style",
      "brand_name": "",
      "food_type": "Generic"
    },
    {
      "food_id": "6921",
      "food_name": "Chunky Style Vegetable Soup",
      "food_url": "https://foods.fatsecret.com/calories-nutrition/generic/vegetable-soup-chunky-style",
      "brand_name": "",
      "food_type": "Generic"
    },
    {
      "food_id": "3564",
      "food_name": "Pannetone (Italian-Style Sweetbread)",
      "food_url": "https://foods.fatsecret.com/calories-nutrition/generic/pannetone-(italian-style-sweetbread)",
      "brand_name": "",
      "food_type": "Generic"
    },
    {
      "food_id": "4846",
      "food_name": "Mexican Style Meatless Tamale",
      "food_url": "https://foods.fatsecret.com/calories-nutrition/generic/tamale-plain-meatless-no-sauce-mexican-style",
      "brand_name": "",
      "food_type": "Generic"
    },
    {
      "food_id": "1882",
      "food_name": "Country Style Pork Sausage",
      "food_url": "https://foods.fatsecret.com/calories-nutrition/generic/pork-sausage-country-style-fresh-cooked",
      "brand_name": "",
      "food_type": "Generic"
    },
    {
      "food_id": "6792",
      "food_name": "Kim Chee Style Cabbage",
      "food_url": "https://foods.fatsecret.com/calories-nutrition/generic/cabbage-kim-chee-style",
      "brand_name": "",
      "food_type": "Generic"
    },
    {
      "food_id": "6813",
      "food_name": "Hawaiian Style Pickled Radishes",
      "food_url": "https://foods.fatsecret.com/calories-nutrition/generic/radishes-pickled-hawaiian-style",
      "brand_name": "",
      "food_type": "Generic"
    },
    {
      "food_id": "1434",
      "food_name": "Oriental Style Dehydrated Pork",
      "food_url": "https://foods.fatsecret.com/calories-nutrition/generic/pork-dehydrated-oriental-style",
      "brand_name": "",
      "food_type": "Generic"
    },
    {
      "food_id": "7692",
      "food_name": "Puerto Rican Style Sangria",
      "food_url": "https://foods.fatsecret.com/calories-nutrition/generic/sangria-puerto-rican-style",
      "brand_name": "",
      "food_type": "Generic"
    },
    {
      "food_id": "3011",
      "food_name": "Chunky Style Chicken Noodle Soup",
      "food_url": "https://foods.fatsecret.com/calories-nutrition/generic/chicken-noodle-soup-chunky-style",
      "brand_name": "",
      "food_type": "Generic"
    },
    {
      "food_id": "6519",
      "food_name": "Cream Style Yellow Corn (Canned)",
      "food_url": "https://foods.fatsecret.com/calories-nutrition/generic/corn-yellow-from-canned-cream-style",
      "brand_name": "",
      "food_type": "Generic"
    },
    {
      "food_id": "7329",
      "food_name": "Puerto Rican Style Pineapple Candy",
      "food_url": "https://foods.fatsecret.com/calories-nutrition/generic/pineapple-candy-puerto-rican-style",
      "brand_name": "",
      "food_type": "Generic"
    },
    {
      "food_id": "3214",
      "food_name": "Barbecue, Ranch Style or Mexican Style Chili Beans",
      "food_url": "https://foods.fatsecret.com/calories-nutrition/generic/chili-beans-barbecue-beans-ranch-style-beans-or-mexican--style-beans",
      "brand_name": "",
      "food_type": "Generic"
    },
    {
      "food_id": "1200",
      "food_name": "Puerto Rican Style Custard (Flan)",
      "food_url": "https://foods.fatsecret.com/calories-nutrition/generic/custard-puerto-rican-style-(flan)",
      "brand_name": "",
      "food_type": "Generic"
    },
    {
      "food_id": "5208",
      "food_name": "Oriental Style Sweet Barley Soup",
      "food_url": "https://foods.fatsecret.com/calories-nutrition/generic/barley-soup-sweet-with-or-without-nuts-oriental-style",
      "brand_name": "",
      "food_type": "Generic"
    },
    {
      "food_id": "2265",
      "food_name": "Chinese Style Lemon Chicken",
      "food_url": "https://foods.fatsecret.com/calories-nutrition/generic/lemon-chicken-chinese-style",
      "brand_name": "",
      "food_type": "Generic"
    },
    {
      "food_id": "6515",
      "food_name": "Cream Style Corn (Canned)",
      "food_url": "https://foods.fatsecret.com/calories-nutrition/generic/corn-from-canned-cream-style",
      "brand_name": "",
      "food_type": "Generic"
    },
    {
      "food_id": "3263",
      "food_name": "Puerto Rican Style Stewed Cowpeas",
      "food_url": "https://foods.fatsecret.com/calories-nutrition/generic/stewed-cowpeas-puerto-rican-style",
      "brand_name": "",
      "food_type": "Generic"
    },
    {
      "food_id": "2212",
      "food_name": "Puerto Rican Style Meatballs (Albondigas)",
      "food_url": "https://foods.fatsecret.com/calories-nutrition/generic/meatballs-puerto-rican-style-(albondigas)",
      "brand_name": "",
      "food_type": "Generic"
    },
    {
      "food_id": "2295",
      "food_name": "Puerto Rican Style Stewed Codfish",
      "food_url": "https://foods.fatsecret.com/calories-nutrition/generic/stewed-codfish-puerto-rican-style",
      "brand_name": "",
      "food_type": "Generic"
    },
    {
      "food_id": "4391",
      "food_name": "Puerto Rican Style Fried Dumpling",
      "food_url": "https://foods.fatsecret.com/calories-nutrition/generic/dumpling-fried-puerto-rican-style",
      "brand_name": "",
      "food_type": "Generic"
    },
    {
      "food_id": "2984",
      "food_name": "Chunky Style Beef Noodle Soup",
      "food_url": "https://foods.fatsecret.com/calories-nutrition/generic/beef-noodle-soup-chunky-style",
      "brand_name": "",
      "food_type": "Generic"
    },
    {
      "food_id": "2991",
      "food_name": "Chunky Style Beef Stroganoff Soup",
      "food_url": "https://foods.fatsecret.com/calories-nutrition/generic/beef-stroganoff-soup-chunky-style",
      "brand_name": "",
      "food_type": "Generic"
    },
    {
      "food_id": "3005",
      "food_name": "Mexican Style Chicken Broth Soup",
      "food_url": "https://foods.fatsecret.com/calories-nutrition/generic/mexican-style-chicken-broth-soup-stock",
      "brand_name": "",
      "food_type": "Generic"
    },
    {
      "food_id": "3018",
      "food_name": "Chunky Style Turkey Noodle Soup",
      "food_url": "https://foods.fatsecret.com/calories-nutrition/generic/turkey-noodle-soup-chunky-style",
      "brand_name": "",
      "food_type": "Generic"
    },
    {
      "food_id": "40730",
      "food_name": "Oriental Style Pork (Dehydrated)",
      "food_url": "https://foods.fatsecret.com/calories-nutrition/usda/oriental-style-pork-(dehydrated)",
      "brand_name": "",
      "food_type": "Generic"
    },
    {
      "food_id": "3887",
      "food_name": "El Salvadorian Style Quezadilla Cake",
      "food_url": "https://foods.fatsecret.com/calories-nutrition/generic/cake-quezadilla-el-salvadorian-style",
      "brand_name": "",
      "food_type": "Generic"
    },
    {
      "food_id": "4020",
      "food_name": "Pizzelle Cookie (Italian Style Wafer)",
      "food_url": "https://foods.fatsecret.com/calories-nutrition/generic/cookie-pizzelle-(italian-style-wafer)",
      "brand_name": "",
      "food_type": "Generic"
    },
    {
      "food_id": "2977",
      "food_name": "Chunky Style Chili Beef Soup",
      "food_url": "https://foods.fatsecret.com/calories-nutrition/generic/chili-beef-soup-chunky-style",
      "brand_name": "",
      "food_type": "Generic"
    },
    {
      "food_id": "3258",
      "food_name": "Puerto Rican Style Stewed Chickpeas",
      "food_url": "https://foods.fatsecret.com/calories-nutrition/generic/stewed-chickpeas-puerto-rican-style",
      "brand_name": "",
      "food_type": "Generic"
    },
    {
      "food_id": "3706",
      "food_name": "Injera (American-Style Ethiopian Bread)",
      "food_url": "https://foods.fatsecret.com/calories-nutrition/generic/injera-(american-style-ethiopian-bread)",
      "brand_name": "",
      "food_type": "Generic"
    },
    {
      "food_id": "6099",
      "food_name": "Puerto Rican Style Pumpkin Fritters",
      "food_url": "https://foods.fatsecret.com/calories-nutrition/generic/pumpkin-fritters-puerto-rican-style",
      "brand_name": "",
      "food_type": "Generic"
    },
    {
      "food_id": "2230",
      "food_name": "Puerto Rican Style Stewed Pork",
      "food_url": "https://foods.fatsecret.com/calories-nutrition/generic/stewed-pork-puerto-rican-style",
      "brand_name": "",
      "food_type": "Generic"
    },
    {
      "food_id": "6523",
      "food_name": "Cream Style White Corn (Canned)",
      "food_url": "https://foods.fatsecret.com/calories-nutrition/generic/corn-white-from-canned-cream-style",
      "brand_name": "",
      "food_type": "Generic"
    },
    {
      "food_id": "6937",
      "food_name": "Chunky Style Vegetable Beef Soup",
      "food_url": "https://foods.fatsecret.com/calories-nutrition/generic/vegetable-beef-soup-chunky-style",
      "brand_name": "",
      "food_type": "Generic"
    },
    {
      "food_id": "7275",
      "food_name": "Puerto Rican Style Coconut Candy",
      "food_url": "https://foods.fatsecret.com/calories-nutrition/generic/coconut-candy-puerto-rican-style",
      "brand_name": "",
      "food_type": "Generic"
    },
    {
      "food_id": "2417",
      "food_name": "Puerto Rican Style Stewed Salmon (Salmon Guisado)",
      "food_url": "https://foods.fatsecret.com/calories-nutrition/generic/stewed-salmon-puerto-rican-style-(salmon-guisado)",
      "brand_name": "",
      "food_type": "Generic"
    },
    {
      "food_id": "2427",
      "food_name": "Puerto Rican Style Breaded Brains (Sesos Rebosados)",
      "food_url": "https://foods.fatsecret.com/calories-nutrition/generic/breaded-brains-puerto-rican-style-(sesos-rebosados)",
      "brand_name": "",
      "food_type": "Generic"
    },
    {
      "food_id": "2571",
      "food_name": "Puerto Rican Style Stewed Variety Meats (Gandinga)",
      "food_url": "https://foods.fatsecret.com/calories-nutrition/generic/stewed-variety-meats-puerto-rican-style-(mostly-liver)-(gandinga)",
      "brand_name": "",
      "food_type": "Generic"
    },
    {
      "food_id": "2658",
      "food_name": "Puerto Rican Style Chicken or Turkey Fricassee",
      "food_url": "https://foods.fatsecret.com/calories-nutrition/generic/chicken-or-turkey-fricassee-no-potatoes-puerto-rican-style-(assume-with-sauce)",
      "brand_name": "",
      "food_type": "Generic"
    },
    {
      "food_id": "2704",
      "food_name": "Puerto Rican Style Stewed Chitterlings (Cuajo Guisado)",
      "food_url": "https://foods.fatsecret.com/calories-nutrition/generic/stewed-chitterlings-puerto-rican-style-(cuajo-guisado)",
      "brand_name": "",
      "food_type": "Generic"
    },
    {
      "food_id": "3049",
      "food_name": "Puerto Rican Style Codfish Soup with Noodles",
      "food_url": "https://foods.fatsecret.com/calories-nutrition/generic/codfish-soup-with-noodles-puerto-rican-style",
      "brand_name": "",
      "food_type": "Generic"
    },
    {
      "food_id": "3086",
      "food_name": "Puerto Rican Style Stuffed Pot Roast Gravy",
      "food_url": "https://foods.fatsecret.com/calories-nutrition/generic/gravy-meat-based-from-puerto-rican-style-stuffed-pot-roast",
      "brand_name": "",
      "food_type": "Generic"
    }
  ]
}