{
  "restaurant": "Kibun",
  "total_items": 3,
  "pages_extracted": 1,
  "total_search_results": 3,
  "discovery_method": "Dynamic restaurant discovery",
  "last_updated": "2025-09-07T01:41:00.479Z",
  "source": "FatSecret Platform API (OAuth 1.0)",
  "extraction_method": "Discovered restaurant with comprehensive extraction",
  "github_url": "https://raw.githubusercontent.com/YOUR_USERNAME/food-database/main/restaurants/kibun.json",
  "items": [
    {
      "food_id": "11430026",
      "food_name": "Healthy Noodle",
      "food_url": "https://foods.fatsecret.com/calories-nutrition/kibun/healthy-noodle",
      "brand_name": "Kibun",
      "food_type": "Brand"
    },
    {
      "food_id": "96022450",
      "food_name": "Takoyaki",
      "food_url": "https://foods.fatsecret.com/calories-nutrition/kibun/takoyaki",
      "brand_name": "Kibun",
      "food_type": "Brand"
    },
    {
      "food_id": "78552531",
      "food_name": "Umami Oden Japanese Style Hot Pot",
      "food_url": "https://foods.fatsecret.com/calories-nutrition/kibun/umami-oden-japanese-style-hot-pot",
      "brand_name": "Kibun",
      "food_type": "Brand"
    }
  ]
}