{
  "restaurant": "Randalls",
  "total_items": 3,
  "pages_extracted": 1,
  "total_search_results": 3,
  "discovery_method": "Dynamic restaurant discovery",
  "last_updated": "2025-09-07T01:47:13.889Z",
  "source": "FatSecret Platform API (OAuth 1.0)",
  "extraction_method": "Discovered restaurant with comprehensive extraction",
  "github_url": "https://raw.githubusercontent.com/YOUR_USERNAME/food-database/main/restaurants/randalls.json",
  "items": [
    {
      "food_id": "80396",
      "food_name": "Pinto Beans",
      "food_url": "https://foods.fatsecret.com/calories-nutrition/randalls/pinto-beans",
      "brand_name": "Randalls",
      "food_type": "Brand"
    },
    {
      "food_id": "80315",
      "food_name": "Beef Gravy",
      "food_url": "https://foods.fatsecret.com/calories-nutrition/randalls/beef-gravy",
      "brand_name": "Randalls",
      "food_type": "Brand"
    },
    {
      "food_id": "80395",
      "food_name": "Deluxe Mixed Beans",
      "food_url": "https://foods.fatsecret.com/calories-nutrition/randalls/deluxe-mixed-beans",
      "brand_name": "Randalls",
      "food_type": "Brand"
    }
  ]
}