{
  "brand_name": "Atlanta Bread Company",
  "total_items": 195,
  "pages_extracted": 6,
  "total_search_results": 4318,
  "discovery_method": "Dynamic brand discovery",
  "last_updated": "2025-09-07T15:51:16.696Z",
  "source": "FatSecret Platform API (OAuth 1.0)",
  "extraction_method": "Discovered brand with comprehensive extraction",
  "github_url": "https://raw.githubusercontent.com/YOUR_USERNAME/food-database/main/brands/atlanta_bread_company.json",
  "items": [
    {
      "food_id": "74170981",
      "food_name": "Mediterranean Foccacia Bread",
      "food_url": "https://foods.fatsecret.com/calories-nutrition/atlanta-bread-company/mediterranean-foccacia-bread",
      "brand_name": "Atlanta Bread Company",
      "food_type": "Brand"
    },
    {
      "food_id": "74170357",
      "food_name": "Bagel - Everything",
      "food_url": "https://foods.fatsecret.com/calories-nutrition/atlanta-bread-company/bagel-everything",
      "brand_name": "Atlanta Bread Company",
      "food_type": "Brand"
    },
    {
      "food_id": "74170359",
      "food_name": "Bagel - Plain",
      "food_url": "https://foods.fatsecret.com/calories-nutrition/atlanta-bread-company/bagel-plain",
      "brand_name": "Atlanta Bread Company",
      "food_type": "Brand"
    },
    {
      "food_id": "74170841",
      "food_name": "Foccacia/Panini Bread, 1 Slice",
      "food_url": "https://foods.fatsecret.com/calories-nutrition/atlanta-bread-company/foccacia-panini-bread-1-slice",
      "brand_name": "Atlanta Bread Company",
      "food_type": "Brand"
    },
    {
      "food_id": "74171041",
      "food_name": "Muffin - Banana Nut Muffin Top",
      "food_url": "https://foods.fatsecret.com/calories-nutrition/atlanta-bread-company/muffin-banana-nut-muffin-top",
      "brand_name": "Atlanta Bread Company",
      "food_type": "Brand"
    },
    {
      "food_id": "74170897",
      "food_name": "Hot Pastrami Sandwich",
      "food_url": "https://foods.fatsecret.com/calories-nutrition/atlanta-bread-company/hot-pastrami-sandwich",
      "brand_name": "Atlanta Bread Company",
      "food_type": "Brand"
    },
    {
      "food_id": "74171172",
      "food_name": "Veggie Sandwich",
      "food_url": "https://foods.fatsecret.com/calories-nutrition/atlanta-bread-company/veggie-sandwich",
      "brand_name": "Atlanta Bread Company",
      "food_type": "Brand"
    },
    {
      "food_id": "74171123",
      "food_name": "Scrambled Eggs",
      "food_url": "https://foods.fatsecret.com/calories-nutrition/atlanta-bread-company/scrambled-eggs",
      "brand_name": "Atlanta Bread Company",
      "food_type": "Brand"
    },
    {
      "food_id": "74170849",
      "food_name": "French Baguette, 1 Slice",
      "food_url": "https://foods.fatsecret.com/calories-nutrition/atlanta-bread-company/french-baguette-1-slice",
      "brand_name": "Atlanta Bread Company",
      "food_type": "Brand"
    },
    {
      "food_id": "74170876",
      "food_name": "Grilled Four Cheese Sandwich",
      "food_url": "https://foods.fatsecret.com/calories-nutrition/atlanta-bread-company/grilled-four-cheese-sandwich",
      "brand_name": "Atlanta Bread Company",
      "food_type": "Brand"
    },
    {
      "food_id": "74171043",
      "food_name": "Muffin - Blueberry Muffin Top",
      "food_url": "https://foods.fatsecret.com/calories-nutrition/atlanta-bread-company/muffin-blueberry-muffin-top",
      "brand_name": "Atlanta Bread Company",
      "food_type": "Brand"
    },
    {
      "food_id": "74170730",
      "food_name": "Croissant - Almond",
      "food_url": "https://foods.fatsecret.com/calories-nutrition/atlanta-bread-company/croissant-almond",
      "brand_name": "Atlanta Bread Company",
      "food_type": "Brand"
    },
    {
      "food_id": "74171148",
      "food_name": "Sourdough Bread, Slice",
      "food_url": "https://foods.fatsecret.com/calories-nutrition/atlanta-bread-company/sourdough-bread-slice",
      "brand_name": "Atlanta Bread Company",
      "food_type": "Brand"
    },
    {
      "food_id": "31064",
      "food_name": "Chicken Pesto Panini",
      "food_url": "https://foods.fatsecret.com/calories-nutrition/atlanta-bread-company/chicken-pesto-panini",
      "brand_name": "Atlanta Bread Company",
      "food_type": "Brand"
    },
    {
      "food_id": "74171062",
      "food_name": "Muffin - Pistachio Muffin",
      "food_url": "https://foods.fatsecret.com/calories-nutrition/atlanta-bread-company/muffin-pistachio-muffin",
      "brand_name": "Atlanta Bread Company",
      "food_type": "Brand"
    },
    {
      "food_id": "74170884",
      "food_name": "Ham & Swiss Egg White Omelette",
      "food_url": "https://foods.fatsecret.com/calories-nutrition/atlanta-bread-company/ham-swiss-egg-white-omelette",
      "brand_name": "Atlanta Bread Company",
      "food_type": "Brand"
    },
    {
      "food_id": "74170870",
      "food_name": "French Bread, 1 Slice",
      "food_url": "https://foods.fatsecret.com/calories-nutrition/atlanta-bread-company/french-bread-1-slice",
      "brand_name": "Atlanta Bread Company",
      "food_type": "Brand"
    },
    {
      "food_id": "74170690",
      "food_name": "Cinnamon Raisin Bread, 1 Slice",
      "food_url": "https://foods.fatsecret.com/calories-nutrition/atlanta-bread-company/cinnamon-raisin-bread-1-slice",
      "brand_name": "Atlanta Bread Company",
      "food_type": "Brand"
    },
    {
      "food_id": "74171120",
      "food_name": "Scoop: Tuna Salad",
      "food_url": "https://foods.fatsecret.com/calories-nutrition/atlanta-bread-company/scoop-tuna-salad",
      "brand_name": "Atlanta Bread Company",
      "food_type": "Brand"
    },
    {
      "food_id": "74171057",
      "food_name": "Muffin - Granny Apple Cinnamon",
      "food_url": "https://foods.fatsecret.com/calories-nutrition/atlanta-bread-company/muffin-granny-apple-cinnamon",
      "brand_name": "Atlanta Bread Company",
      "food_type": "Brand"
    },
    {
      "food_id": "74170539",
      "food_name": "Bowl Blueberry Banana with Yogurt",
      "food_url": "https://foods.fatsecret.com/calories-nutrition/atlanta-bread-company/bowl-blueberry-banana-with-yogurt",
      "brand_name": "Atlanta Bread Company",
      "food_type": "Brand"
    },
    {
      "food_id": "74171042",
      "food_name": "Muffin - Blueberry",
      "food_url": "https://foods.fatsecret.com/calories-nutrition/atlanta-bread-company/muffin-blueberry",
      "brand_name": "Atlanta Bread Company",
      "food_type": "Brand"
    },
    {
      "food_id": "74170356",
      "food_name": "Bagel - Cinnamon Raisin",
      "food_url": "https://foods.fatsecret.com/calories-nutrition/atlanta-bread-company/bagel-cinnamon-raisin",
      "brand_name": "Atlanta Bread Company",
      "food_type": "Brand"
    },
    {
      "food_id": "74170887",
      "food_name": "Ham Sandwich",
      "food_url": "https://foods.fatsecret.com/calories-nutrition/atlanta-bread-company/ham-sandwich",
      "brand_name": "Atlanta Bread Company",
      "food_type": "Brand"
    },
    {
      "food_id": "74170547",
      "food_name": "Bowl Mediterranean",
      "food_url": "https://foods.fatsecret.com/calories-nutrition/atlanta-bread-company/bowl-mediterranean",
      "brand_name": "Atlanta Bread Company",
      "food_type": "Brand"
    },
    {
      "food_id": "74170734",
      "food_name": "Croissant - Chocolate",
      "food_url": "https://foods.fatsecret.com/calories-nutrition/atlanta-bread-company/croissant-chocolate",
      "brand_name": "Atlanta Bread Company",
      "food_type": "Brand"
    },
    {
      "food_id": "74171146",
      "food_name": "Smoothie - Strawberry",
      "food_url": "https://foods.fatsecret.com/calories-nutrition/atlanta-bread-company/smoothie-strawberry",
      "brand_name": "Atlanta Bread Company",
      "food_type": "Brand"
    },
    {
      "food_id": "74170931",
      "food_name": "Kids PB & J Sandwich",
      "food_url": "https://foods.fatsecret.com/calories-nutrition/atlanta-bread-company/kids-pb-j-sandwich",
      "brand_name": "Atlanta Bread Company",
      "food_type": "Brand"
    },
    {
      "food_id": "74171157",
      "food_name": "Tomato & Onion Foccacia, 1 Slice",
      "food_url": "https://foods.fatsecret.com/calories-nutrition/atlanta-bread-company/tomato-onion-foccacia-1-slice",
      "brand_name": "Atlanta Bread Company",
      "food_type": "Brand"
    },
    {
      "food_id": "74170672",
      "food_name": "Chicken Parmesan, Panini",
      "food_url": "https://foods.fatsecret.com/calories-nutrition/atlanta-bread-company/chicken-parmesan-panini",
      "brand_name": "Atlanta Bread Company",
      "food_type": "Brand"
    },
    {
      "food_id": "74171103",
      "food_name": "Pumpernickel Bread, 1 Slice",
      "food_url": "https://foods.fatsecret.com/calories-nutrition/atlanta-bread-company/pumpernickel-bread-1-slice",
      "brand_name": "Atlanta Bread Company",
      "food_type": "Brand"
    },
    {
      "food_id": "74170361",
      "food_name": "Bagel - Poppy Seed",
      "food_url": "https://foods.fatsecret.com/calories-nutrition/atlanta-bread-company/bagel-poppy-seed",
      "brand_name": "Atlanta Bread Company",
      "food_type": "Brand"
    },
    {
      "food_id": "74170665",
      "food_name": "Caramel Machiatto - Short",
      "food_url": "https://foods.fatsecret.com/calories-nutrition/atlanta-bread-company/caramel-machiatto-short",
      "brand_name": "Atlanta Bread Company",
      "food_type": "Brand"
    },
    {
      "food_id": "74170732",
      "food_name": "Croissant - Cheese",
      "food_url": "https://foods.fatsecret.com/calories-nutrition/atlanta-bread-company/croissant-cheese",
      "brand_name": "Atlanta Bread Company",
      "food_type": "Brand"
    },
    {
      "food_id": "74171055",
      "food_name": "Muffin - Chocolate Choc Chip Muffin",
      "food_url": "https://foods.fatsecret.com/calories-nutrition/atlanta-bread-company/muffin-chocolate-choc-chip-muffin",
      "brand_name": "Atlanta Bread Company",
      "food_type": "Brand"
    },
    {
      "food_id": "74170738",
      "food_name": "Croissant - Strawberries & Cream",
      "food_url": "https://foods.fatsecret.com/calories-nutrition/atlanta-bread-company/croissant-strawberries-cream",
      "brand_name": "Atlanta Bread Company",
      "food_type": "Brand"
    },
    {
      "food_id": "74170886",
      "food_name": "Ham & Swiss Omelette",
      "food_url": "https://foods.fatsecret.com/calories-nutrition/atlanta-bread-company/ham-swiss-omelette",
      "brand_name": "Atlanta Bread Company",
      "food_type": "Brand"
    },
    {
      "food_id": "74170741",
      "food_name": "Cuban Panini",
      "food_url": "https://foods.fatsecret.com/calories-nutrition/atlanta-bread-company/cuban-panini",
      "brand_name": "Atlanta Bread Company",
      "food_type": "Brand"
    },
    {
      "food_id": "74171189",
      "food_name": "Smoothie - Pineapple Mango",
      "food_url": "https://foods.fatsecret.com/calories-nutrition/atlanta-bread-company/smoothie-pineapple-mango",
      "brand_name": "Atlanta Bread Company",
      "food_type": "Brand"
    },
    {
      "food_id": "74171056",
      "food_name": "Muffin- Glorious Morning",
      "food_url": "https://foods.fatsecret.com/calories-nutrition/atlanta-bread-company/muffin-glorious-morning",
      "brand_name": "Atlanta Bread Company",
      "food_type": "Brand"
    },
    {
      "food_id": "74171151",
      "food_name": "Sticky Bun",
      "food_url": "https://foods.fatsecret.com/calories-nutrition/atlanta-bread-company/sticky-bun",
      "brand_name": "Atlanta Bread Company",
      "food_type": "Brand"
    },
    {
      "food_id": "74171115",
      "food_name": "Scoop: Chicken Salad",
      "food_url": "https://foods.fatsecret.com/calories-nutrition/atlanta-bread-company/scoop-chicken-salad",
      "brand_name": "Atlanta Bread Company",
      "food_type": "Brand"
    },
    {
      "food_id": "74171147",
      "food_name": "Spanish Omelette",
      "food_url": "https://foods.fatsecret.com/calories-nutrition/atlanta-bread-company/spanish-omelette",
      "brand_name": "Atlanta Bread Company",
      "food_type": "Brand"
    },
    {
      "food_id": "74170535",
      "food_name": "Black Bean & Corn",
      "food_url": "https://foods.fatsecret.com/calories-nutrition/atlanta-bread-company/black-bean-corn",
      "brand_name": "Atlanta Bread Company",
      "food_type": "Brand"
    },
    {
      "food_id": "74170736",
      "food_name": "Croissant - French",
      "food_url": "https://foods.fatsecret.com/calories-nutrition/atlanta-bread-company/croissant-french",
      "brand_name": "Atlanta Bread Company",
      "food_type": "Brand"
    },
    {
      "food_id": "74170819",
      "food_name": "Danish - Apple",
      "food_url": "https://foods.fatsecret.com/calories-nutrition/atlanta-bread-company/danish-apple",
      "brand_name": "Atlanta Bread Company",
      "food_type": "Brand"
    },
    {
      "food_id": "74171052",
      "food_name": "Muffin - Cranberry Nut Muffin Top",
      "food_url": "https://foods.fatsecret.com/calories-nutrition/atlanta-bread-company/muffin-cranberry-nut-muffin-top",
      "brand_name": "Atlanta Bread Company",
      "food_type": "Brand"
    },
    {
      "food_id": "74171064",
      "food_name": "New England Clam Chowder Soup",
      "food_url": "https://foods.fatsecret.com/calories-nutrition/atlanta-bread-company/new-england-clam-chowder-soup",
      "brand_name": "Atlanta Bread Company",
      "food_type": "Brand"
    },
    {
      "food_id": "1099704",
      "food_name": "Turkey Club Panini",
      "food_url": "https://foods.fatsecret.com/calories-nutrition/atlanta-bread-company/turkey-club-panini",
      "brand_name": "Atlanta Bread Company",
      "food_type": "Brand"
    },
    {
      "food_id": "74170836",
      "food_name": "Egg Cheese & Turkey Sausage (502Kcal)",
      "food_url": "https://foods.fatsecret.com/calories-nutrition/atlanta-bread-company/egg-cheese-turkey-sausage-(502kcal)",
      "brand_name": "Atlanta Bread Company",
      "food_type": "Brand"
    },
    {
      "food_id": "74170878",
      "food_name": "Greek Yogurt w/ Granola",
      "food_url": "https://foods.fatsecret.com/calories-nutrition/atlanta-bread-company/greek-yogurt-w-granola",
      "brand_name": "Atlanta Bread Company",
      "food_type": "Brand"
    },
    {
      "food_id": "74171105",
      "food_name": "Roast Beef Sandwich",
      "food_url": "https://foods.fatsecret.com/calories-nutrition/atlanta-bread-company/roast-beef-sandwich",
      "brand_name": "Atlanta Bread Company",
      "food_type": "Brand"
    },
    {
      "food_id": "74171136",
      "food_name": "Side: Breaded Chicken Breast",
      "food_url": "https://foods.fatsecret.com/calories-nutrition/atlanta-bread-company/side-breaded-chicken-breast",
      "brand_name": "Atlanta Bread Company",
      "food_type": "Brand"
    },
    {
      "food_id": "1350010",
      "food_name": "Florentine Omelette",
      "food_url": "https://foods.fatsecret.com/calories-nutrition/atlanta-bread-company/florentine-omelette",
      "brand_name": "Atlanta Bread Company",
      "food_type": "Brand"
    },
    {
      "food_id": "1100532",
      "food_name": "House Salad",
      "food_url": "https://foods.fatsecret.com/calories-nutrition/atlanta-bread-company/house-salad",
      "brand_name": "Atlanta Bread Company",
      "food_type": "Brand"
    },
    {
      "food_id": "74170350",
      "food_name": "Bagel - Blueberry",
      "food_url": "https://foods.fatsecret.com/calories-nutrition/atlanta-bread-company/bagel-blueberry",
      "brand_name": "Atlanta Bread Company",
      "food_type": "Brand"
    },
    {
      "food_id": "74170669",
      "food_name": "Chicken Dumpling Soup, Bowl",
      "food_url": "https://foods.fatsecret.com/calories-nutrition/atlanta-bread-company/chicken-dumpling-soup-bowl",
      "brand_name": "Atlanta Bread Company",
      "food_type": "Brand"
    },
    {
      "food_id": "74171135",
      "food_name": "Side: Bacon 1 Slice",
      "food_url": "https://foods.fatsecret.com/calories-nutrition/atlanta-bread-company/side-bacon-1-slice",
      "brand_name": "Atlanta Bread Company",
      "food_type": "Brand"
    },
    {
      "food_id": "74171137",
      "food_name": "Side: Breakfast Potatoes",
      "food_url": "https://foods.fatsecret.com/calories-nutrition/atlanta-bread-company/side-breakfast-potatoes",
      "brand_name": "Atlanta Bread Company",
      "food_type": "Brand"
    },
    {
      "food_id": "74171154",
      "food_name": "Tomato & Bacon Omelette",
      "food_url": "https://foods.fatsecret.com/calories-nutrition/atlanta-bread-company/tomato-bacon-omelette",
      "brand_name": "Atlanta Bread Company",
      "food_type": "Brand"
    },
    {
      "food_id": "74171176",
      "food_name": "Waldorf Chicken Salad Signature Sandwich",
      "food_url": "https://foods.fatsecret.com/calories-nutrition/atlanta-bread-company/waldorf-chicken-salad-signature-sandwich",
      "brand_name": "Atlanta Bread Company",
      "food_type": "Brand"
    },
    {
      "food_id": "74170597",
      "food_name": "California Avocado Signature (800Kcal)",
      "food_url": "https://foods.fatsecret.com/calories-nutrition/atlanta-bread-company/california-avocado-signature-(800kcal)",
      "brand_name": "Atlanta Bread Company",
      "food_type": "Brand"
    },
    {
      "food_id": "74170873",
      "food_name": "French Onion Soup, Bowl",
      "food_url": "https://foods.fatsecret.com/calories-nutrition/atlanta-bread-company/french-onion-soup-bowl",
      "brand_name": "Atlanta Bread Company",
      "food_type": "Brand"
    },
    {
      "food_id": "74171046",
      "food_name": "Muffin - Chocolate Chip Muffin Top",
      "food_url": "https://foods.fatsecret.com/calories-nutrition/atlanta-bread-company/muffin-chocolate-chip-muffin-top",
      "brand_name": "Atlanta Bread Company",
      "food_type": "Brand"
    },
    {
      "food_id": "74171050",
      "food_name": "Muffin - Cranberry Nut",
      "food_url": "https://foods.fatsecret.com/calories-nutrition/atlanta-bread-company/muffin-cranberry-nut",
      "brand_name": "Atlanta Bread Company",
      "food_type": "Brand"
    },
    {
      "food_id": "74170536",
      "food_name": "Bowl Blueberry Banana with Oatmeal",
      "food_url": "https://foods.fatsecret.com/calories-nutrition/atlanta-bread-company/bowl-blueberry-banana-with-oatmeal",
      "brand_name": "Atlanta Bread Company",
      "food_type": "Brand"
    },
    {
      "food_id": "74170674",
      "food_name": "Chicken Pesto Panini with Kettle",
      "food_url": "https://foods.fatsecret.com/calories-nutrition/atlanta-bread-company/chicken-pesto-panini-with-kettle",
      "brand_name": "Atlanta Bread Company",
      "food_type": "Brand"
    },
    {
      "food_id": "74171138",
      "food_name": "Side: Cream Cheese (2 oz)",
      "food_url": "https://foods.fatsecret.com/calories-nutrition/atlanta-bread-company/side-cream-cheese-(2-oz)",
      "brand_name": "Atlanta Bread Company",
      "food_type": "Brand"
    },
    {
      "food_id": "74171188",
      "food_name": "Muffin - Banana Nut",
      "food_url": "https://foods.fatsecret.com/calories-nutrition/atlanta-bread-company/muffin-banana-nut",
      "brand_name": "Atlanta Bread Company",
      "food_type": "Brand"
    },
    {
      "food_id": "74170373",
      "food_name": "Bagel - Multi Whole Grain",
      "food_url": "https://foods.fatsecret.com/calories-nutrition/atlanta-bread-company/bagel-multi-whole-grain",
      "brand_name": "Atlanta Bread Company",
      "food_type": "Brand"
    },
    {
      "food_id": "74170835",
      "food_name": "Egg Cheese & Turkey Sausage (499Kcal)",
      "food_url": "https://foods.fatsecret.com/calories-nutrition/atlanta-bread-company/egg-cheese-turkey-sausage-(499kcal)",
      "brand_name": "Atlanta Bread Company",
      "food_type": "Brand"
    },
    {
      "food_id": "74170880",
      "food_name": "Grilled Caprese Sandwich",
      "food_url": "https://foods.fatsecret.com/calories-nutrition/atlanta-bread-company/grilled-caprese-sandwich",
      "brand_name": "Atlanta Bread Company",
      "food_type": "Brand"
    },
    {
      "food_id": "74171053",
      "food_name": "Muffin - Chocolate Choc Chip",
      "food_url": "https://foods.fatsecret.com/calories-nutrition/atlanta-bread-company/muffin-chocolate-choc-chip",
      "brand_name": "Atlanta Bread Company",
      "food_type": "Brand"
    },
    {
      "food_id": "74171110",
      "food_name": "Roasted Turkey Sandwich",
      "food_url": "https://foods.fatsecret.com/calories-nutrition/atlanta-bread-company/roasted-turkey-sandwich",
      "brand_name": "Atlanta Bread Company",
      "food_type": "Brand"
    },
    {
      "food_id": "74170891",
      "food_name": "Honey Wheat Bread, 1 Slice",
      "food_url": "https://foods.fatsecret.com/calories-nutrition/atlanta-bread-company/honey-wheat-bread-1-slice",
      "brand_name": "Atlanta Bread Company",
      "food_type": "Brand"
    },
    {
      "food_id": "74170834",
      "food_name": "Egg Cheese & Ham Breakfast (508Kcal)",
      "food_url": "https://foods.fatsecret.com/calories-nutrition/atlanta-bread-company/egg-cheese-ham-breakfast-(508kcal)",
      "brand_name": "Atlanta Bread Company",
      "food_type": "Brand"
    },
    {
      "food_id": "74170874",
      "food_name": "French Toast",
      "food_url": "https://foods.fatsecret.com/calories-nutrition/atlanta-bread-company/french-toast",
      "brand_name": "Atlanta Bread Company",
      "food_type": "Brand"
    },
    {
      "food_id": "74170923",
      "food_name": "Hot Spiced Chai Tea",
      "food_url": "https://foods.fatsecret.com/calories-nutrition/atlanta-bread-company/hot-spiced-chai-tea",
      "brand_name": "Atlanta Bread Company",
      "food_type": "Brand"
    },
    {
      "food_id": "74170976",
      "food_name": "Latte - Tall",
      "food_url": "https://foods.fatsecret.com/calories-nutrition/atlanta-bread-company/latte-tall",
      "brand_name": "Atlanta Bread Company",
      "food_type": "Brand"
    },
    {
      "food_id": "74170541",
      "food_name": "Bowl Strawberry Banana with Yogurt",
      "food_url": "https://foods.fatsecret.com/calories-nutrition/atlanta-bread-company/bowl-strawberry-banana-with-yogurt",
      "brand_name": "Atlanta Bread Company",
      "food_type": "Brand"
    },
    {
      "food_id": "74170821",
      "food_name": "Egg & Cheese Breakfast Sandwich (524Kcal)",
      "food_url": "https://foods.fatsecret.com/calories-nutrition/atlanta-bread-company/egg-cheese-breakfast-sandwich-(524kcal)",
      "brand_name": "Atlanta Bread Company",
      "food_type": "Brand"
    },
    {
      "food_id": "74170837",
      "food_name": "Egg, Cheese, & Pork Sausage (546Kcal)",
      "food_url": "https://foods.fatsecret.com/calories-nutrition/atlanta-bread-company/egg-cheese-pork-sausage-(546kcal)",
      "brand_name": "Atlanta Bread Company",
      "food_type": "Brand"
    },
    {
      "food_id": "74170993",
      "food_name": "Mini Croissant",
      "food_url": "https://foods.fatsecret.com/calories-nutrition/atlanta-bread-company/mini-croissant",
      "brand_name": "Atlanta Bread Company",
      "food_type": "Brand"
    },
    {
      "food_id": "74171094",
      "food_name": "Tomato Basil Soup, Bowl",
      "food_url": "https://foods.fatsecret.com/calories-nutrition/atlanta-bread-company/tomato-basil-soup-bowl",
      "brand_name": "Atlanta Bread Company",
      "food_type": "Brand"
    },
    {
      "food_id": "74171097",
      "food_name": "Pecan Roll",
      "food_url": "https://foods.fatsecret.com/calories-nutrition/atlanta-bread-company/pecan-roll",
      "brand_name": "Atlanta Bread Company",
      "food_type": "Brand"
    },
    {
      "food_id": "74171108",
      "food_name": "Roast Beef Sandwich with Kettle",
      "food_url": "https://foods.fatsecret.com/calories-nutrition/atlanta-bread-company/roast-beef-sandwich-with-kettle",
      "brand_name": "Atlanta Bread Company",
      "food_type": "Brand"
    },
    {
      "food_id": "74170712",
      "food_name": "Multigrain Cranberry Bread, 1 Slice",
      "food_url": "https://foods.fatsecret.com/calories-nutrition/atlanta-bread-company/multigrain-cranberry-bread-1-slice",
      "brand_name": "Atlanta Bread Company",
      "food_type": "Brand"
    },
    {
      "food_id": "74171113",
      "food_name": "Rye Bread, 1 Slice",
      "food_url": "https://foods.fatsecret.com/calories-nutrition/atlanta-bread-company/rye-bread-1-slice",
      "brand_name": "Atlanta Bread Company",
      "food_type": "Brand"
    },
    {
      "food_id": "1099743",
      "food_name": "Greek Salad",
      "food_url": "https://foods.fatsecret.com/calories-nutrition/atlanta-bread-company/greek-salad",
      "brand_name": "Atlanta Bread Company",
      "food_type": "Brand"
    },
    {
      "food_id": "2886835",
      "food_name": "Cinnamon Roll",
      "food_url": "https://foods.fatsecret.com/calories-nutrition/atlanta-bread-company/cinnamon-roll",
      "brand_name": "Atlanta Bread Company",
      "food_type": "Brand"
    },
    {
      "food_id": "6788642",
      "food_name": "Mini Cream Cheese Croissants",
      "food_url": "https://foods.fatsecret.com/calories-nutrition/atlanta-bread-company/mini-cream-cheese-croissants",
      "brand_name": "Atlanta Bread Company",
      "food_type": "Brand"
    },
    {
      "food_id": "74170304",
      "food_name": "ABC Signature Sandwich",
      "food_url": "https://foods.fatsecret.com/calories-nutrition/atlanta-bread-company/abc-signature-sandwich",
      "brand_name": "Atlanta Bread Company",
      "food_type": "Brand"
    },
    {
      "food_id": "74170348",
      "food_name": "Bagel - Asiago Cheese",
      "food_url": "https://foods.fatsecret.com/calories-nutrition/atlanta-bread-company/bagel-asiago-cheese",
      "brand_name": "Atlanta Bread Company",
      "food_type": "Brand"
    },
    {
      "food_id": "74170358",
      "food_name": "Bagel - Onion",
      "food_url": "https://foods.fatsecret.com/calories-nutrition/atlanta-bread-company/bagel-onion",
      "brand_name": "Atlanta Bread Company",
      "food_type": "Brand"
    },
    {
      "food_id": "74170379",
      "food_name": "Twice Baked Potato Bowl",
      "food_url": "https://foods.fatsecret.com/calories-nutrition/atlanta-bread-company/twice-baked-potato-bowl",
      "brand_name": "Atlanta Bread Company",
      "food_type": "Brand"
    },
    {
      "food_id": "74170544",
      "food_name": "Bowl Power",
      "food_url": "https://foods.fatsecret.com/calories-nutrition/atlanta-bread-company/bowl-power",
      "brand_name": "Atlanta Bread Company",
      "food_type": "Brand"
    },
    {
      "food_id": "74170571",
      "food_name": "Broccoli Cheese Soup, Bowl",
      "food_url": "https://foods.fatsecret.com/calories-nutrition/atlanta-bread-company/broccoli-cheese-soup-bowl",
      "brand_name": "Atlanta Bread Company",
      "food_type": "Brand"
    },
    {
      "food_id": "74170679",
      "food_name": "White Chicken Chili Soup, Bowl",
      "food_url": "https://foods.fatsecret.com/calories-nutrition/atlanta-bread-company/white-chicken-chili-soup-bowl",
      "brand_name": "Atlanta Bread Company",
      "food_type": "Brand"
    },
    {
      "food_id": "74170719",
      "food_name": "Cookies - Sugar 3Oz",
      "food_url": "https://foods.fatsecret.com/calories-nutrition/atlanta-bread-company/cookies-sugar-3oz",
      "brand_name": "Atlanta Bread Company",
      "food_type": "Brand"
    },
    {
      "food_id": "74170725",
      "food_name": "Cookies - M&M Choc Chip 3Oz",
      "food_url": "https://foods.fatsecret.com/calories-nutrition/atlanta-bread-company/cookies-m-m-choc-chip-3oz",
      "brand_name": "Atlanta Bread Company",
      "food_type": "Brand"
    },
    {
      "food_id": "74170820",
      "food_name": "Danish - Cheese",
      "food_url": "https://foods.fatsecret.com/calories-nutrition/atlanta-bread-company/danish-cheese",
      "brand_name": "Atlanta Bread Company",
      "food_type": "Brand"
    },
    {
      "food_id": "74170918",
      "food_name": "Bagel - Sesame Seed",
      "food_url": "https://foods.fatsecret.com/calories-nutrition/atlanta-bread-company/bagel-sesame-seed",
      "brand_name": "Atlanta Bread Company",
      "food_type": "Brand"
    },
    {
      "food_id": "74170980",
      "food_name": "Margherita Flatbread",
      "food_url": "https://foods.fatsecret.com/calories-nutrition/atlanta-bread-company/margherita-flatbread",
      "brand_name": "Atlanta Bread Company",
      "food_type": "Brand"
    },
    {
      "food_id": "74170998",
      "food_name": "Mocha - Short",
      "food_url": "https://foods.fatsecret.com/calories-nutrition/atlanta-bread-company/mocha-short",
      "brand_name": "Atlanta Bread Company",
      "food_type": "Brand"
    },
    {
      "food_id": "74171001",
      "food_name": "Morning Classic Bacon",
      "food_url": "https://foods.fatsecret.com/calories-nutrition/atlanta-bread-company/morning-classic-bacon",
      "brand_name": "Atlanta Bread Company",
      "food_type": "Brand"
    },
    {
      "food_id": "74171099",
      "food_name": "Pepperoni Flatbread",
      "food_url": "https://foods.fatsecret.com/calories-nutrition/atlanta-bread-company/pepperoni-flatbread",
      "brand_name": "Atlanta Bread Company",
      "food_type": "Brand"
    },
    {
      "food_id": "74171149",
      "food_name": "Steakhouse Panini",
      "food_url": "https://foods.fatsecret.com/calories-nutrition/atlanta-bread-company/steakhouse-panini",
      "brand_name": "Atlanta Bread Company",
      "food_type": "Brand"
    },
    {
      "food_id": "74171163",
      "food_name": "Tuna Salad Sandwich",
      "food_url": "https://foods.fatsecret.com/calories-nutrition/atlanta-bread-company/tuna-salad-sandwich",
      "brand_name": "Atlanta Bread Company",
      "food_type": "Brand"
    },
    {
      "food_id": "74170347",
      "food_name": "Wild Alaskan Salmon (Add on)",
      "food_url": "https://foods.fatsecret.com/calories-nutrition/atlanta-bread-company/wild-alaskan-salmon-(add-on)",
      "brand_name": "Atlanta Bread Company",
      "food_type": "Brand"
    },
    {
      "food_id": "74170375",
      "food_name": "Baja Chicken Enchilada Soup, Bowl",
      "food_url": "https://foods.fatsecret.com/calories-nutrition/atlanta-bread-company/baja-chicken-enchilada-soup-bowl",
      "brand_name": "Atlanta Bread Company",
      "food_type": "Brand"
    },
    {
      "food_id": "74170381",
      "food_name": "Balsamic Blue Salad",
      "food_url": "https://foods.fatsecret.com/calories-nutrition/atlanta-bread-company/balsamic-blue-salad",
      "brand_name": "Atlanta Bread Company",
      "food_type": "Brand"
    },
    {
      "food_id": "74170533",
      "food_name": "Beef & Blue Flatbread",
      "food_url": "https://foods.fatsecret.com/calories-nutrition/atlanta-bread-company/beef-blue-flatbread",
      "brand_name": "Atlanta Bread Company",
      "food_type": "Brand"
    },
    {
      "food_id": "74170675",
      "food_name": "Chicken Salad Sandwich",
      "food_url": "https://foods.fatsecret.com/calories-nutrition/atlanta-bread-company/chicken-salad-sandwich",
      "brand_name": "Atlanta Bread Company",
      "food_type": "Brand"
    },
    {
      "food_id": "74170685",
      "food_name": "Chopstix Chicken Salad",
      "food_url": "https://foods.fatsecret.com/calories-nutrition/atlanta-bread-company/chopstix-chicken-salad",
      "brand_name": "Atlanta Bread Company",
      "food_type": "Brand"
    },
    {
      "food_id": "74170727",
      "food_name": "Cookies - Chocolate Chip 1.33Oz",
      "food_url": "https://foods.fatsecret.com/calories-nutrition/atlanta-bread-company/cookies-chocolate-chip-133oz",
      "brand_name": "Atlanta Bread Company",
      "food_type": "Brand"
    },
    {
      "food_id": "74170832",
      "food_name": "Egg Cheese & Ham Breakfast (506Kcal)",
      "food_url": "https://foods.fatsecret.com/calories-nutrition/atlanta-bread-company/egg-cheese-ham-breakfast-(506kcal)",
      "brand_name": "Atlanta Bread Company",
      "food_type": "Brand"
    },
    {
      "food_id": "74170875",
      "food_name": "Fruit Salad",
      "food_url": "https://foods.fatsecret.com/calories-nutrition/atlanta-bread-company/fruit-salad",
      "brand_name": "Atlanta Bread Company",
      "food_type": "Brand"
    },
    {
      "food_id": "74170877",
      "food_name": "Greek Salad - Half",
      "food_url": "https://foods.fatsecret.com/calories-nutrition/atlanta-bread-company/greek-salad-half",
      "brand_name": "Atlanta Bread Company",
      "food_type": "Brand"
    },
    {
      "food_id": "74170881",
      "food_name": "Grilled Caprese Sandwich with Kettle",
      "food_url": "https://foods.fatsecret.com/calories-nutrition/atlanta-bread-company/grilled-caprese-sandwich-with-kettle",
      "brand_name": "Atlanta Bread Company",
      "food_type": "Brand"
    },
    {
      "food_id": "74170898",
      "food_name": "Hot Pastrami Sandwich with Kettle",
      "food_url": "https://foods.fatsecret.com/calories-nutrition/atlanta-bread-company/hot-pastrami-sandwich-with-kettle",
      "brand_name": "Atlanta Bread Company",
      "food_type": "Brand"
    },
    {
      "food_id": "74170927",
      "food_name": "Iced Coffee",
      "food_url": "https://foods.fatsecret.com/calories-nutrition/atlanta-bread-company/iced-coffee",
      "brand_name": "Atlanta Bread Company",
      "food_type": "Brand"
    },
    {
      "food_id": "74170928",
      "food_name": "Kids Cheese Pizza/Flatbread",
      "food_url": "https://foods.fatsecret.com/calories-nutrition/atlanta-bread-company/kids-cheese-pizza-flatbread",
      "brand_name": "Atlanta Bread Company",
      "food_type": "Brand"
    },
    {
      "food_id": "74170985",
      "food_name": "Mini Brownie - Chocolate Ganache",
      "food_url": "https://foods.fatsecret.com/calories-nutrition/atlanta-bread-company/mini-brownie-chocolate-ganache",
      "brand_name": "Atlanta Bread Company",
      "food_type": "Brand"
    },
    {
      "food_id": "74170991",
      "food_name": "Mini Brownie - Plain",
      "food_url": "https://foods.fatsecret.com/calories-nutrition/atlanta-bread-company/mini-brownie-plain",
      "brand_name": "Atlanta Bread Company",
      "food_type": "Brand"
    },
    {
      "food_id": "74170995",
      "food_name": "Mocha - Tall",
      "food_url": "https://foods.fatsecret.com/calories-nutrition/atlanta-bread-company/mocha-tall",
      "brand_name": "Atlanta Bread Company",
      "food_type": "Brand"
    },
    {
      "food_id": "74171061",
      "food_name": "Muffin - Magic Pumpkin Nut Muffin",
      "food_url": "https://foods.fatsecret.com/calories-nutrition/atlanta-bread-company/muffin-magic-pumpkin-nut-muffin",
      "brand_name": "Atlanta Bread Company",
      "food_type": "Brand"
    },
    {
      "food_id": "74171112",
      "food_name": "Roasted Turkey Sandwich with Kettle",
      "food_url": "https://foods.fatsecret.com/calories-nutrition/atlanta-bread-company/roasted-turkey-sandwich-with-kettle",
      "brand_name": "Atlanta Bread Company",
      "food_type": "Brand"
    },
    {
      "food_id": "74171141",
      "food_name": "Side: Pickle Spear",
      "food_url": "https://foods.fatsecret.com/calories-nutrition/atlanta-bread-company/side-pickle-spear",
      "brand_name": "Atlanta Bread Company",
      "food_type": "Brand"
    },
    {
      "food_id": "74171179",
      "food_name": "Waldorf Chicken Salad Signature Sandwich with Kettle Chips",
      "food_url": "https://foods.fatsecret.com/calories-nutrition/atlanta-bread-company/waldorf-chicken-salad-signature-sandwich-with-kettle-chips",
      "brand_name": "Atlanta Bread Company",
      "food_type": "Brand"
    },
    {
      "food_id": "74171063",
      "food_name": "Ninegrain Bread, Slice",
      "food_url": "https://foods.fatsecret.com/calories-nutrition/atlanta-bread-company/ninegrain-bread-slice",
      "brand_name": "Atlanta Bread Company",
      "food_type": "Brand"
    },
    {
      "food_id": "74170383",
      "food_name": "Balsamic Blue Salad - Half",
      "food_url": "https://foods.fatsecret.com/calories-nutrition/atlanta-bread-company/balsamic-blue-salad-half",
      "brand_name": "Atlanta Bread Company",
      "food_type": "Brand"
    },
    {
      "food_id": "74170540",
      "food_name": "Bowl Strawberry Banana with Oatmeal",
      "food_url": "https://foods.fatsecret.com/calories-nutrition/atlanta-bread-company/bowl-strawberry-banana-with-oatmeal",
      "brand_name": "Atlanta Bread Company",
      "food_type": "Brand"
    },
    {
      "food_id": "74170607",
      "food_name": "California Avocado Signature (950Kcal)",
      "food_url": "https://foods.fatsecret.com/calories-nutrition/atlanta-bread-company/california-avocado-signature-(950kcal)",
      "brand_name": "Atlanta Bread Company",
      "food_type": "Brand"
    },
    {
      "food_id": "74170609",
      "food_name": "Cappuccino - Short",
      "food_url": "https://foods.fatsecret.com/calories-nutrition/atlanta-bread-company/cappuccino-short",
      "brand_name": "Atlanta Bread Company",
      "food_type": "Brand"
    },
    {
      "food_id": "74170667",
      "food_name": "Chardonnay Brie Salad (No Dressing)",
      "food_url": "https://foods.fatsecret.com/calories-nutrition/atlanta-bread-company/chardonnay-brie-salad-(no-dressing)",
      "brand_name": "Atlanta Bread Company",
      "food_type": "Brand"
    },
    {
      "food_id": "74170671",
      "food_name": "Chicken Noodle Soup, Bowl",
      "food_url": "https://foods.fatsecret.com/calories-nutrition/atlanta-bread-company/chicken-noodle-soup-bowl",
      "brand_name": "Atlanta Bread Company",
      "food_type": "Brand"
    },
    {
      "food_id": "74170676",
      "food_name": "Chicken Salad Sandwich with Kettle",
      "food_url": "https://foods.fatsecret.com/calories-nutrition/atlanta-bread-company/chicken-salad-sandwich-with-kettle",
      "brand_name": "Atlanta Bread Company",
      "food_type": "Brand"
    },
    {
      "food_id": "74170682",
      "food_name": "Chili with Beef Soup, Bowl",
      "food_url": "https://foods.fatsecret.com/calories-nutrition/atlanta-bread-company/chili-with-beef-soup-bowl",
      "brand_name": "Atlanta Bread Company",
      "food_type": "Brand"
    },
    {
      "food_id": "74170710",
      "food_name": "Cobb Salad - Half",
      "food_url": "https://foods.fatsecret.com/calories-nutrition/atlanta-bread-company/cobb-salad-half",
      "brand_name": "Atlanta Bread Company",
      "food_type": "Brand"
    },
    {
      "food_id": "74170713",
      "food_name": "Cookies - Oatmeal Raisin 3Oz",
      "food_url": "https://foods.fatsecret.com/calories-nutrition/atlanta-bread-company/cookies-oatmeal-raisin-3oz",
      "brand_name": "Atlanta Bread Company",
      "food_type": "Brand"
    },
    {
      "food_id": "74170714",
      "food_name": "Cookies - Double Peanut Butter 3Oz",
      "food_url": "https://foods.fatsecret.com/calories-nutrition/atlanta-bread-company/cookies-double-peanut-butter-3oz",
      "brand_name": "Atlanta Bread Company",
      "food_type": "Brand"
    },
    {
      "food_id": "74170716",
      "food_name": "Cookies - Chocolate Chip 3Oz",
      "food_url": "https://foods.fatsecret.com/calories-nutrition/atlanta-bread-company/cookies-chocolate-chip-3oz",
      "brand_name": "Atlanta Bread Company",
      "food_type": "Brand"
    },
    {
      "food_id": "74170729",
      "food_name": "Cookies - Red Velvet 4.5Oz",
      "food_url": "https://foods.fatsecret.com/calories-nutrition/atlanta-bread-company/cookies-red-velvet-45oz",
      "brand_name": "Atlanta Bread Company",
      "food_type": "Brand"
    },
    {
      "food_id": "74170827",
      "food_name": "Egg Cheese & Bacon Breakfast (453Kcal)",
      "food_url": "https://foods.fatsecret.com/calories-nutrition/atlanta-bread-company/egg-cheese-bacon-breakfast-(453kcal)",
      "brand_name": "Atlanta Bread Company",
      "food_type": "Brand"
    },
    {
      "food_id": "74170830",
      "food_name": "Egg Cheese & Bacon Breakfast (456Kcal)",
      "food_url": "https://foods.fatsecret.com/calories-nutrition/atlanta-bread-company/egg-cheese-bacon-breakfast-(456kcal)",
      "brand_name": "Atlanta Bread Company",
      "food_type": "Brand"
    },
    {
      "food_id": "74170838",
      "food_name": "Egg, Cheese, & Pork Sausage (549Kcal)",
      "food_url": "https://foods.fatsecret.com/calories-nutrition/atlanta-bread-company/egg-cheese-pork-sausage-(549kcal)",
      "brand_name": "Atlanta Bread Company",
      "food_type": "Brand"
    },
    {
      "food_id": "74170842",
      "food_name": "Four Cheese Flatbread",
      "food_url": "https://foods.fatsecret.com/calories-nutrition/atlanta-bread-company/four-cheese-flatbread",
      "brand_name": "Atlanta Bread Company",
      "food_type": "Brand"
    },
    {
      "food_id": "74170890",
      "food_name": "Ham Sandwich with Kettle Chips",
      "food_url": "https://foods.fatsecret.com/calories-nutrition/atlanta-bread-company/ham-sandwich-with-kettle-chips",
      "brand_name": "Atlanta Bread Company",
      "food_type": "Brand"
    },
    {
      "food_id": "74170894",
      "food_name": "Hot Chocolate - Tall",
      "food_url": "https://foods.fatsecret.com/calories-nutrition/atlanta-bread-company/hot-chocolate-tall",
      "brand_name": "Atlanta Bread Company",
      "food_type": "Brand"
    },
    {
      "food_id": "74170896",
      "food_name": "Hot Chocolate - Short",
      "food_url": "https://foods.fatsecret.com/calories-nutrition/atlanta-bread-company/hot-chocolate-short",
      "brand_name": "Atlanta Bread Company",
      "food_type": "Brand"
    },
    {
      "food_id": "74170922",
      "food_name": "Croissant - Apple",
      "food_url": "https://foods.fatsecret.com/calories-nutrition/atlanta-bread-company/croissant-apple",
      "brand_name": "Atlanta Bread Company",
      "food_type": "Brand"
    },
    {
      "food_id": "74170978",
      "food_name": "Side Mandarin Oranges",
      "food_url": "https://foods.fatsecret.com/calories-nutrition/atlanta-bread-company/side-mandarin-oranges",
      "brand_name": "Atlanta Bread Company",
      "food_type": "Brand"
    },
    {
      "food_id": "74171004",
      "food_name": "Morning Classic Ham",
      "food_url": "https://foods.fatsecret.com/calories-nutrition/atlanta-bread-company/morning-classic-ham",
      "brand_name": "Atlanta Bread Company",
      "food_type": "Brand"
    },
    {
      "food_id": "74171044",
      "food_name": "Muffin - Chocolate Chip",
      "food_url": "https://foods.fatsecret.com/calories-nutrition/atlanta-bread-company/muffin-chocolate-chip",
      "brand_name": "Atlanta Bread Company",
      "food_type": "Brand"
    },
    {
      "food_id": "74171065",
      "food_name": "Oatmeal Plain",
      "food_url": "https://foods.fatsecret.com/calories-nutrition/atlanta-bread-company/oatmeal-plain",
      "brand_name": "Atlanta Bread Company",
      "food_type": "Brand"
    },
    {
      "food_id": "74171077",
      "food_name": "Butternut Squash Soup, Bowl",
      "food_url": "https://foods.fatsecret.com/calories-nutrition/atlanta-bread-company/butternut-squash-soup-bowl",
      "brand_name": "Atlanta Bread Company",
      "food_type": "Brand"
    },
    {
      "food_id": "74171100",
      "food_name": "Potato Salad",
      "food_url": "https://foods.fatsecret.com/calories-nutrition/atlanta-bread-company/potato-salad",
      "brand_name": "Atlanta Bread Company",
      "food_type": "Brand"
    },
    {
      "food_id": "74171124",
      "food_name": "Side: Apple",
      "food_url": "https://foods.fatsecret.com/calories-nutrition/atlanta-bread-company/side-apple",
      "brand_name": "Atlanta Bread Company",
      "food_type": "Brand"
    },
    {
      "food_id": "74171140",
      "food_name": "Side: Ham",
      "food_url": "https://foods.fatsecret.com/calories-nutrition/atlanta-bread-company/side-ham",
      "brand_name": "Atlanta Bread Company",
      "food_type": "Brand"
    },
    {
      "food_id": "74171143",
      "food_name": "Side: Turkey Sausage",
      "food_url": "https://foods.fatsecret.com/calories-nutrition/atlanta-bread-company/side-turkey-sausage",
      "brand_name": "Atlanta Bread Company",
      "food_type": "Brand"
    },
    {
      "food_id": "74171153",
      "food_name": "Thai Green Flatbread",
      "food_url": "https://foods.fatsecret.com/calories-nutrition/atlanta-bread-company/thai-green-flatbread",
      "brand_name": "Atlanta Bread Company",
      "food_type": "Brand"
    },
    {
      "food_id": "74171165",
      "food_name": "Tuna Salad Sandwich with Kettle",
      "food_url": "https://foods.fatsecret.com/calories-nutrition/atlanta-bread-company/tuna-salad-sandwich-with-kettle",
      "brand_name": "Atlanta Bread Company",
      "food_type": "Brand"
    },
    {
      "food_id": "74171167",
      "food_name": "Turkey Bacon Avocado Signature (777Kcal)",
      "food_url": "https://foods.fatsecret.com/calories-nutrition/atlanta-bread-company/turkey-bacon-avocado-signature-(777kcal)",
      "brand_name": "Atlanta Bread Company",
      "food_type": "Brand"
    },
    {
      "food_id": "74171169",
      "food_name": "Turkey Bacon Avocado Signature (927Kcal)",
      "food_url": "https://foods.fatsecret.com/calories-nutrition/atlanta-bread-company/turkey-bacon-avocado-signature-(927kcal)",
      "brand_name": "Atlanta Bread Company",
      "food_type": "Brand"
    },
    {
      "food_id": "74171170",
      "food_name": "Turkey Club Panini with Kettle Chips",
      "food_url": "https://foods.fatsecret.com/calories-nutrition/atlanta-bread-company/turkey-club-panini-with-kettle-chips",
      "brand_name": "Atlanta Bread Company",
      "food_type": "Brand"
    },
    {
      "food_id": "74171171",
      "food_name": "Turkey Sausage & Egg Whites",
      "food_url": "https://foods.fatsecret.com/calories-nutrition/atlanta-bread-company/turkey-sausage-egg-whites",
      "brand_name": "Atlanta Bread Company",
      "food_type": "Brand"
    },
    {
      "food_id": "74170323",
      "food_name": "ABC Signature Sandwich with Kettle",
      "food_url": "https://foods.fatsecret.com/calories-nutrition/atlanta-bread-company/abc-signature-sandwich-with-kettle",
      "brand_name": "Atlanta Bread Company",
      "food_type": "Brand"
    },
    {
      "food_id": "74170345",
      "food_name": "Chicken Breast (Add on)",
      "food_url": "https://foods.fatsecret.com/calories-nutrition/atlanta-bread-company/chicken-breast-(add-on)",
      "brand_name": "Atlanta Bread Company",
      "food_type": "Brand"
    },
    {
      "food_id": "74170346",
      "food_name": "Shrimp (Add on)",
      "food_url": "https://foods.fatsecret.com/calories-nutrition/atlanta-bread-company/shrimp-(add-on)",
      "brand_name": "Atlanta Bread Company",
      "food_type": "Brand"
    },
    {
      "food_id": "74170532",
      "food_name": "Bella Chicken Sandwich with Kettle",
      "food_url": "https://foods.fatsecret.com/calories-nutrition/atlanta-bread-company/bella-chicken-sandwich-with-kettle",
      "brand_name": "Atlanta Bread Company",
      "food_type": "Brand"
    },
    {
      "food_id": "74170543",
      "food_name": "Bowl Southwest with Bacon",
      "food_url": "https://foods.fatsecret.com/calories-nutrition/atlanta-bread-company/bowl-southwest-with-bacon",
      "brand_name": "Atlanta Bread Company",
      "food_type": "Brand"
    },
    {
      "food_id": "74170545",
      "food_name": "Bowl Tex Mex",
      "food_url": "https://foods.fatsecret.com/calories-nutrition/atlanta-bread-company/bowl-tex-mex",
      "brand_name": "Atlanta Bread Company",
      "food_type": "Brand"
    },
    {
      "food_id": "74170583",
      "food_name": "Caesar Salad",
      "food_url": "https://foods.fatsecret.com/calories-nutrition/atlanta-bread-company/caesar-salad",
      "brand_name": "Atlanta Bread Company",
      "food_type": "Brand"
    },
    {
      "food_id": "74170587",
      "food_name": "Caesar Salad - Half",
      "food_url": "https://foods.fatsecret.com/calories-nutrition/atlanta-bread-company/caesar-salad-half",
      "brand_name": "Atlanta Bread Company",
      "food_type": "Brand"
    },
    {
      "food_id": "74170593",
      "food_name": "Cafechilla - Kona Mocha",
      "food_url": "https://foods.fatsecret.com/calories-nutrition/atlanta-bread-company/cafechilla-kona-mocha",
      "brand_name": "Atlanta Bread Company",
      "food_type": "Brand"
    },
    {
      "food_id": "74170663",
      "food_name": "Caramel Machiatto - Tall",
      "food_url": "https://foods.fatsecret.com/calories-nutrition/atlanta-bread-company/caramel-machiatto-tall",
      "brand_name": "Atlanta Bread Company",
      "food_type": "Brand"
    },
    {
      "food_id": "74170678",
      "food_name": "Chicken with Organic Wild Rice",
      "food_url": "https://foods.fatsecret.com/calories-nutrition/atlanta-bread-company/chicken-with-organic-wild-rice",
      "brand_name": "Atlanta Bread Company",
      "food_type": "Brand"
    },
    {
      "food_id": "74170686",
      "food_name": "Chopstix Chicken Salad - Half",
      "food_url": "https://foods.fatsecret.com/calories-nutrition/atlanta-bread-company/chopstix-chicken-salad-half",
      "brand_name": "Atlanta Bread Company",
      "food_type": "Brand"
    },
    {
      "food_id": "74170693",
      "food_name": "Cobb Salad",
      "food_url": "https://foods.fatsecret.com/calories-nutrition/atlanta-bread-company/cobb-salad",
      "brand_name": "Atlanta Bread Company",
      "food_type": "Brand"
    },
    {
      "food_id": "74170723",
      "food_name": "Cookies - Chocolate Chunk 3Oz",
      "food_url": "https://foods.fatsecret.com/calories-nutrition/atlanta-bread-company/cookies-chocolate-chunk-3oz",
      "brand_name": "Atlanta Bread Company",
      "food_type": "Brand"
    },
    {
      "food_id": "74170742",
      "food_name": "Cuban Panini with Kettle Chips",
      "food_url": "https://foods.fatsecret.com/calories-nutrition/atlanta-bread-company/cuban-panini-with-kettle-chips",
      "brand_name": "Atlanta Bread Company",
      "food_type": "Brand"
    },
    {
      "food_id": "74170826",
      "food_name": "Egg & Cheese Breakfast Sandwich (527Kcal)",
      "food_url": "https://foods.fatsecret.com/calories-nutrition/atlanta-bread-company/egg-cheese-breakfast-sandwich-(527kcal)",
      "brand_name": "Atlanta Bread Company",
      "food_type": "Brand"
    },
    {
      "food_id": "74170840",
      "food_name": "Fire Roasted Vegetable Soup, Bowl",
      "food_url": "https://foods.fatsecret.com/calories-nutrition/atlanta-bread-company/fire-roasted-vegetable-soup-bowl",
      "brand_name": "Atlanta Bread Company",
      "food_type": "Brand"
    },
    {
      "food_id": "74170920",
      "food_name": "Bella Chicken Sandwich",
      "food_url": "https://foods.fatsecret.com/calories-nutrition/atlanta-bread-company/bella-chicken-sandwich",
      "brand_name": "Atlanta Bread Company",
      "food_type": "Brand"
    },
    {
      "food_id": "74170925",
      "food_name": "House Salad - Half",
      "food_url": "https://foods.fatsecret.com/calories-nutrition/atlanta-bread-company/house-salad-half",
      "brand_name": "Atlanta Bread Company",
      "food_type": "Brand"
    },
    {
      "food_id": "74170929",
      "food_name": "Kids Grilled Cheese Sandwich",
      "food_url": "https://foods.fatsecret.com/calories-nutrition/atlanta-bread-company/kids-grilled-cheese-sandwich",
      "brand_name": "Atlanta Bread Company",
      "food_type": "Brand"
    },
    {
      "food_id": "74170975",
      "food_name": "Kids Penne",
      "food_url": "https://foods.fatsecret.com/calories-nutrition/atlanta-bread-company/kids-penne",
      "brand_name": "Atlanta Bread Company",
      "food_type": "Brand"
    },
    {
      "food_id": "74170977",
      "food_name": "Latte - Short",
      "food_url": "https://foods.fatsecret.com/calories-nutrition/atlanta-bread-company/latte-short",
      "brand_name": "Atlanta Bread Company",
      "food_type": "Brand"
    },
    {
      "food_id": "74170983",
      "food_name": "Mini Brownie - Butter Cream",
      "food_url": "https://foods.fatsecret.com/calories-nutrition/atlanta-bread-company/mini-brownie-butter-cream",
      "brand_name": "Atlanta Bread Company",
      "food_type": "Brand"
    },
    {
      "food_id": "74171006",
      "food_name": "Morning Classic Turkey Sausage",
      "food_url": "https://foods.fatsecret.com/calories-nutrition/atlanta-bread-company/morning-classic-turkey-sausage",
      "brand_name": "Atlanta Bread Company",
      "food_type": "Brand"
    },
    {
      "food_id": "74171059",
      "food_name": "Muffin - Magic Pumpkin Nut",
      "food_url": "https://foods.fatsecret.com/calories-nutrition/atlanta-bread-company/muffin-magic-pumpkin-nut",
      "brand_name": "Atlanta Bread Company",
      "food_type": "Brand"
    },
    {
      "food_id": "74171117",
      "food_name": "Scoop: Chicken Waldorf",
      "food_url": "https://foods.fatsecret.com/calories-nutrition/atlanta-bread-company/scoop-chicken-waldorf",
      "brand_name": "Atlanta Bread Company",
      "food_type": "Brand"
    },
    {
      "food_id": "74171142",
      "food_name": "Side: Sausage (Pork)",
      "food_url": "https://foods.fatsecret.com/calories-nutrition/atlanta-bread-company/side-sausage-(pork)",
      "brand_name": "Atlanta Bread Company",
      "food_type": "Brand"
    },
    {
      "food_id": "74171150",
      "food_name": "Steakhouse Panini with Kettle Chips",
      "food_url": "https://foods.fatsecret.com/calories-nutrition/atlanta-bread-company/steakhouse-panini-with-kettle-chips",
      "brand_name": "Atlanta Bread Company",
      "food_type": "Brand"
    },
    {
      "food_id": "74171175",
      "food_name": "Veggie Sandwich with Kettle Chips",
      "food_url": "https://foods.fatsecret.com/calories-nutrition/atlanta-bread-company/veggie-sandwich-with-kettle-chips",
      "brand_name": "Atlanta Bread Company",
      "food_type": "Brand"
    }
  ]
}